omni_pathlib/__init__.py
omni_pathlib/base_path.py
omni_pathlib/exceptions.py
omni_pathlib/py.typed
omni_pathlib/providers/__init__.py
omni_pathlib/providers/http/DEV.md
omni_pathlib/providers/http/__init__.py
omni_pathlib/providers/local/__init__.py
omni_pathlib/providers/s3/__init__.py
omni_pathlib/providers/s3/async_ops.py
omni_pathlib/providers/s3/credentials.py
omni_pathlib/providers/s3/sign_request.py
omni_pathlib/providers/s3/sync_ops.py
omni_pathlib/providers/s3/type_hints.py
omni_pathlib/utils/__init__.py
omni_pathlib/utils/guess_protocol.py
omni_pathlib/utils/is_absolute_path.py
omni_pathlib/utils/join_paths.py
omni_pathlib/utils/parse_url.py
omni_pathlib/utils/raise_for_status_with_text.py
omni_pathlib-0.6.0.dist-info/METADATA
omni_pathlib-0.6.0.dist-info/WHEEL
omni_pathlib-0.6.0.dist-info/RECORD
