Metadata-Version: 2.4
Name: omni_pathlib
Version: 0.6.0
Summary: 一个统一的路径处理库,支持本地文件系统、HTTP 和 S3 存储的路径操作
Project-URL: Homepage, https://github.com/Haskely/omni-pathlib
Project-URL: Repository, https://github.com/Haskely/omni-pathlib
Project-URL: Documentation, https://github.com/Haskely/omni-pathlib#readme
Project-URL: Bug Tracker, https://github.com/Haskely/omni-pathlib/issues
Project-URL: Change Log, https://github.com/Haskely/omni-pathlib/blob/main/CHANGELOG.md
Author-email: Haskely <Haskely@live.com>
Keywords: async,filesystem,http,pathlib,s3
Classifier: Development Status :: 4 - Beta
Classifier: Intended Audience :: Developers
Classifier: License :: OSI Approved :: MIT License
Classifier: Programming Language :: Python :: 3
Classifier: Programming Language :: Python :: 3.10
Classifier: Topic :: Software Development :: Libraries :: Python Modules
Classifier: Topic :: System :: Filesystems
Requires-Python: >=3.10
Requires-Dist: aiohttp>=3.11.11
Requires-Dist: anyio>=4.10.0
Requires-Dist: curl-cffi>=0.10.0
Requires-Dist: loguru>=0.7.3
Requires-Dist: rich>=13.9.4
Requires-Dist: xmltodict>=0.14.2
